{
  "id": "tooling/luxjs-guides/generate-key-pair",
  "title": "Manual Creation of Public-Private Key Pairs using LuxJS",
  "description": "LuxJS is a JavaScript Library for interfacing with the Lux platform. It is built using TypeScript and intended to support both browser and Node.js. The LuxJS library allows one to issue commands to the Lux node APIs.",
  "source": "@site/docs/tooling/luxjs-guides/generate-key-pair.md",
  "sourceDirName": "tooling/luxjs-guides",
  "slug": "/tooling/luxjs-guides/generate-key-pair",
  "permalink": "/tooling/luxjs-guides/generate-key-pair",
  "draft": false,
  "unlisted": false,
  "editUrl": "https://github.com/luxfi/docs/edit/main/docs/tooling/luxjs-guides/generate-key-pair.md",
  "tags": [
    {
      "label": "Tooling",
      "permalink": "/tags/tooling"
    },
    {
      "label": "LuxJS",
      "permalink": "/tags/lux-js"
    }
  ],
  "version": "current",
  "sidebarPosition": 0,
  "frontMatter": {
    "tags": [
      "Tooling",
      "LuxJS"
    ],
    "description": "LuxJS is a JavaScript Library for interfacing with the Lux platform. It is built using TypeScript and intended to support both browser and Node.js. The LuxJS library allows one to issue commands to the Lux node APIs.",
    "pagination_label": "Manual Creation of Public-Private Key Pairs using LuxJS",
    "sidebar_label": "Generate Key Pair",
    "sidebar_position": 0
  },
  "sidebar": "tooling",
  "previous": {
    "title": "LuxJS API Reference",
    "permalink": "/tooling/luxjs-api"
  },
  "next": {
    "title": "Generate a Transaction ID Using LuxJS",
    "permalink": "/tooling/luxjs-guides/generate-a-txid-using-luxjs"
  }
}